tai64converter/__init__.py
tai64converter/_nbdev.py
tai64converter/core.py
tai64converter-0.0.1.dist-info/LICENSE
tai64converter-0.0.1.dist-info/METADATA
tai64converter-0.0.1.dist-info/WHEEL
tai64converter-0.0.1.dist-info/entry_points.txt
tai64converter-0.0.1.dist-info/top_level.txt
tai64converter-0.0.1.dist-info/RECORD
