Metadata-Version: 2.1
Name: tai64converter
Version: 0.0.1
Summary: Encode and decode tai64 values to datetime
Home-page: https://github.com/MikkoFinellEdupower/tai64converter/tree/master/
Author: Mikko Finell
Author-email: mikko.finell@edupower.fi
License: Apache Software License 2.0
Keywords: tai64
Platform: UNKNOWN
Classifier: Development Status :: 3 - Alpha
Classifier: Intended Audience :: Developers
Classifier: License :: OSI Approved :: Apache Software License
Classifier: Natural Language :: English
Classifier: Programming Language :: Python :: 3.8
Requires-Python: >=3.8
Requires-Dist: fastcore
